setup.py
sheetsql/__init__.py
sheetsql/cursor.py
sheetsql/exceptions.py
sheetsql/sheets.py
sheetsql/utils.py
sheetsql.egg-info/PKG-INFO
sheetsql.egg-info/SOURCES.txt
sheetsql.egg-info/dependency_links.txt
sheetsql.egg-info/requires.txt
sheetsql.egg-info/top_level.txt