Metadata-Version: 1.0
Name: sheetsql
Version: 0.0.1
Summary: Google Sheets as a SQL Database
Home-page: https://github.com/SpiesWithin/SheetSQL
Author: SpiesWithin
Author-email: spieswithin@gmail.com
License: MIT
Platform: UNKNOWN
